lingrex/__init__.py
lingrex/align.py
lingrex/borrowing.py
lingrex/cognates.py
lingrex/colex.py
lingrex/copar.py
lingrex/evaluate.py
lingrex/fuzzy.py
lingrex/reconstruct.py
lingrex/regularity.py
lingrex/semirex.py
lingrex/trimming.py
lingrex/util.py
lingrex-1.4.2.dist-info/LICENSE
lingrex-1.4.2.dist-info/METADATA
lingrex-1.4.2.dist-info/WHEEL
lingrex-1.4.2.dist-info/top_level.txt
lingrex-1.4.2.dist-info/RECORD
